LinearResponseVariationalBayes/ConjugateGradient.py
LinearResponseVariationalBayes/DirichletParams.py
LinearResponseVariationalBayes/ExponentialFamilies.py
LinearResponseVariationalBayes/GammaParams.py
LinearResponseVariationalBayes/MatrixParameters.py
LinearResponseVariationalBayes/ModelSensitivity.py
LinearResponseVariationalBayes/Modeling.py
LinearResponseVariationalBayes/NormalParams.py
LinearResponseVariationalBayes/OptimizationUtils.py
LinearResponseVariationalBayes/ParameterDictionary.py
LinearResponseVariationalBayes/Parameters.py
LinearResponseVariationalBayes/ProjectionParams.py
LinearResponseVariationalBayes/SimplexParams.py
LinearResponseVariationalBayes/SparseObjectives.py
LinearResponseVariationalBayes/WishartParams.py
LinearResponseVariationalBayes/__init__.py
LinearResponseVariationalBayes/regression_utils.py
LinearResponseVariationalBayes/test_exponential_families.py
LinearResponseVariationalBayes/test_model_sensitivity.py
LinearResponseVariationalBayes/test_objectives.py
LinearResponseVariationalBayes/test_optimization_utils.py
LinearResponseVariationalBayes/test_regression.py
LinearResponseVariationalBayes/test_variational_bayes.py
LinearResponseVariationalBayes/version.py
LinearResponseVariationalBayes-0.2.1.dist-info/LICENSE.txt
LinearResponseVariationalBayes-0.2.1.dist-info/METADATA
LinearResponseVariationalBayes-0.2.1.dist-info/WHEEL
LinearResponseVariationalBayes-0.2.1.dist-info/top_level.txt
LinearResponseVariationalBayes-0.2.1.dist-info/RECORD
